setup.py
tailall.py
tailall.egg-info/PKG-INFO
tailall.egg-info/SOURCES.txt
tailall.egg-info/dependency_links.txt
tailall.egg-info/entry_points.txt
tailall.egg-info/requires.txt
tailall.egg-info/top_level.txt