Metadata-Version: 1.0
Name: tailall
Version: 0.0.2
Summary: tail every file under a directory
Home-page: UNKNOWN
Author: tengu
Author-email: karasuyamatengu@gmail.com
License: LGPL
Platform: UNKNOWN
Classifier: License :: OSI Approved :: GNU Library or Lesser General Public License (LGPL)
Classifier: Environment :: Console
Classifier: Programming Language :: Python
Classifier: Development Status :: 3 - Alpha
Classifier: Topic :: Utilities
